yaml_workflow/__init__.py
yaml_workflow/__main__.py
yaml_workflow/cli.py
yaml_workflow/engine.py
yaml_workflow/exceptions.py
yaml_workflow/py.typed
yaml_workflow/runner.py
yaml_workflow/state.py
yaml_workflow/step.py
yaml_workflow/template.py
yaml_workflow/types.py
yaml_workflow/workspace.py
yaml_workflow/examples/advanced_hello_world.yaml
yaml_workflow/examples/complex_flow_error_handling.yaml
yaml_workflow/examples/hello_world.yaml
yaml_workflow/examples/python_tasks.yaml
yaml_workflow/examples/template_tasks.yaml
yaml_workflow/examples/test_resume.yaml
yaml_workflow/tasks/__init__.py
yaml_workflow/tasks/base.py
yaml_workflow/tasks/basic_tasks.py
yaml_workflow/tasks/batch.py
yaml_workflow/tasks/batch_context.py
yaml_workflow/tasks/config.py
yaml_workflow/tasks/error_handling.py
yaml_workflow/tasks/file_tasks.py
yaml_workflow/tasks/file_utils.py
yaml_workflow/tasks/noop.py
yaml_workflow/tasks/python_tasks.py
yaml_workflow/tasks/shell_tasks.py
yaml_workflow/tasks/template_tasks.py
yaml_workflow/utils/__init__.py
yaml_workflow/utils/yaml_utils.py
yaml_workflow-0.4.0.dist-info/METADATA
yaml_workflow-0.4.0.dist-info/WHEEL
yaml_workflow-0.4.0.dist-info/entry_points.txt
yaml_workflow-0.4.0.dist-info/licenses/LICENSE
yaml_workflow-0.4.0.dist-info/RECORD
