Metadata-Version: 2.4
Name: yaml-workflow
Version: 0.4.0
Summary: A lightweight, powerful, and flexible workflow engine that executes tasks defined in YAML configuration files
Project-URL: Homepage, https://github.com/orieg/yaml-workflow
Project-URL: Issues, https://github.com/orieg/yaml-workflow/issues
Project-URL: Documentation, https://orieg.github.io/yaml-workflow/
Author-email: Nicolas Brousse <nicolas@brousse.info>
License: MIT License
License-File: LICENSE
Keywords: automation,batch-processing,configuration,data-pipeline,data-processing,distributed-tasks,etl,job-scheduler,modular-workflows,orchestration,parallel-processing,pipeline,process-automation,reports,retry-mechanism,state-management,task-orchestration,task-runner,templating,workflow,workflow-automation,workflow-engine,workflow-management,yaml,yaml-configuration
Classifier: Development Status :: 4 - Beta
Classifier: Intended Audience :: Developers
Classifier: Intended Audience :: Information Technology
Classifier: Intended Audience :: System Administrators
Classifier: License :: OSI Approved :: MIT License
Classifier: Natural Language :: English
Classifier: Operating System :: OS Independent
Classifier: Programming Language :: Python :: 3
Classifier: Programming Language :: Python :: 3.10
Classifier: Programming Language :: Python :: 3.11
Classifier: Programming Language :: Python :: 3.12
Classifier: Programming Language :: Python :: 3.13
Classifier: Topic :: Software Development :: Build Tools
Classifier: Topic :: Software Development :: Libraries :: Application Frameworks
Classifier: Topic :: Software Development :: Libraries :: Python Modules
Classifier: Topic :: System :: Systems Administration
Classifier: Typing :: Typed
Requires-Python: >=3.10
Requires-Dist: click<9.0,>=8.0
Requires-Dist: jinja2<4.0,>=3.0
Requires-Dist: pyyaml<7.0,>=6.0
Provides-Extra: dev
Requires-Dist: black==25.1.0; extra == 'dev'
Requires-Dist: build<2.0.0,>=1.0.0; extra == 'dev'
Requires-Dist: isort<7.0,>=5.0; extra == 'dev'
Requires-Dist: twine<7.0.0,>=4.0.0; extra == 'dev'
Provides-Extra: doc
Requires-Dist: docstring-parser<1.0,>=0.16.0; extra == 'doc'
Requires-Dist: griffe>=0.49.0; extra == 'doc'
Requires-Dist: mkdocs-gen-files<1.0,>=0.5.0; extra == 'doc'
Requires-Dist: mkdocs-literate-nav<1.0,>=0.6.0; extra == 'doc'
Requires-Dist: mkdocs-material<10.0,>=9.6.0; extra == 'doc'
Requires-Dist: mkdocs-section-index<1.0,>=0.3.0; extra == 'doc'
Requires-Dist: mkdocs<2.0,>=1.6.0; extra == 'doc'
Requires-Dist: mkdocstrings[python]<1.0,>=0.29.0; extra == 'doc'
Provides-Extra: test
Requires-Dist: mypy<2.0,>=1.0; extra == 'test'
Requires-Dist: pytest-cov<7.0,>=4.0; extra == 'test'
Requires-Dist: pytest-ordering; extra == 'test'
Requires-Dist: pytest<9.0,>=7.0; extra == 'test'
Requires-Dist: types-pyyaml<7.0,>=6.0; extra == 'test'
